earth_distances/__init__.py
earth_distances/distance_calculation/__init__.py
earth_distances/distance_calculation/harvesini.py
earth_distances/map_plotting/__init__.py
earth_distances/map_plotting/world_map_plot.py
earth_distances-0.0.8.dist-info/METADATA
earth_distances-0.0.8.dist-info/WHEEL
earth_distances-0.0.8.dist-info/top_level.txt
earth_distances-0.0.8.dist-info/RECORD
