Metadata-Version: 2.1
Name: earth-distances
Version: 0.0.8
Summary: Package focused on Earth distance calculation and plotting
Home-page: https://tinyurl.com/2p83nw5z
Author: Gabriel Vinicius Sebastião
Author-email: gabrielvrsas@gmail.com
License: UNKNOWN
Platform: UNKNOWN
Requires-Python: >=3.8.5
Requires-Dist: plotly (>=5.11.0)
